<?xml version = '1.0' encoding = 'UTF-8'?>
<Diagram class="oracle.dbtools.crest.swingui.logical.DPVLogical" name="Logical" id="DB277D24-095A-F9CD-83FA-AB714B5802FB">
<createdBy>darkl</createdBy>
<modifiedBy>darkl</modifiedBy>
<createdTime>2020-02-21 06:49:21 UTC</createdTime>
<autoRoute>false</autoRoute>
<boxInbox>true</boxInbox>
<showLegend>false</showLegend>
<showLabels>false</showLabels>
<showRelAttributes>false</showRelAttributes>
<gridEnabled>false</gridEnabled>
<showGrid>false</showGrid>
<diagramColor>-1</diagramColor>
<display>false</display>
<notation>1</notation>
</Diagram>